nonebot_plugin_sparkapi-2.0.9.dist-info/METADATA
nonebot_plugin_sparkapi-2.0.9.dist-info/WHEEL
nonebot_plugin_sparkapi-2.0.9.dist-info/entry_points.txt
nonebot_plugin_sparkapi-2.0.9.dist-info/licenses/LICENSE
nonebot_plugin_sparkapi/API/ImgGenApi.py
nonebot_plugin_sparkapi/API/PPTGenApi.py
nonebot_plugin_sparkapi/API/SparkApi.py
nonebot_plugin_sparkapi/__init__.py
nonebot_plugin_sparkapi/config.py
nonebot_plugin_sparkapi/funcs.py
nonebot_plugin_sparkapi/matchers/__init__.py
nonebot_plugin_sparkapi/matchers/block_private.py
nonebot_plugin_sparkapi/matchers/chat.py
nonebot_plugin_sparkapi/matchers/clear.py
nonebot_plugin_sparkapi/matchers/help.py
nonebot_plugin_sparkapi/matchers/imggen.py
nonebot_plugin_sparkapi/matchers/pptgen.py
nonebot_plugin_sparkapi/matchers/preset/__init__.py
nonebot_plugin_sparkapi/matchers/preset/base.py
nonebot_plugin_sparkapi/matchers/preset/create.py
nonebot_plugin_sparkapi/matchers/preset/delete.py
nonebot_plugin_sparkapi/matchers/preset/preset.py
nonebot_plugin_sparkapi/matchers/preset/set.py
nonebot_plugin_sparkapi/matchers/preset/show.py
nonebot_plugin_sparkapi/matchers/session/__init__.py
nonebot_plugin_sparkapi/matchers/session/base.py
nonebot_plugin_sparkapi/matchers/session/delete.py
nonebot_plugin_sparkapi/matchers/session/load.py
nonebot_plugin_sparkapi/matchers/session/save.py
nonebot_plugin_sparkapi/matchers/session/session.py
nonebot_plugin_sparkapi/matchers/session/show.py
nonebot_plugin_sparkapi-2.0.9.dist-info/RECORD
