Metadata-Version: 2.1
Name: nonebot_plugin_sparkapi
Version: 2.0.9
Summary: Nonebot2 plugin that calls the official API of the iflyrec SparkDesk for all model versions, defaulting to the current latest
Author-Email: CCLMSY <2502408581@qq.com>
License: MIT
Requires-Python: >=3.10
Requires-Dist: nonebot2>=2.3.3
Requires-Dist: httpx>=0.27.0
Requires-Dist: websockets>=12.0
Requires-Dist: nonebot-plugin-alconna>=0.51.4
Requires-Dist: nonebot-plugin-localstore<1.0.0,>=0.6.0
Requires-Dist: nonebot-plugin-session>=0.3.2
